{
  "conditions": [
    {
      "type": "packedup:is_backpack_enabled",
      "backpack": "iron"
    },
    {
      "type": "supermartijn642corelib:not",
      "condition": {
        "conditions": [
          {
            "backpack": "silver",
            "condition": "packedup:is_backpack_enabled"
          },
          {
            "ore": "ingotSilver",
            "condition": "supermartijn642corelib:ore_dict_populated"
          }
        ],
        "type": "supermartijn642corelib:and"
      }
    },
    {
      "type": "supermartijn642corelib:not",
      "condition": {
        "backpack": "gold",
        "type": "packedup:is_backpack_enabled"
      }
    },
    {
      "type": "supermartijn642corelib:not",
      "condition": {
        "backpack": "diamond",
        "type": "packedup:is_backpack_enabled"
      }
    },
    {
      "type": "packedup:is_backpack_enabled",
      "backpack": "obsidian"
    }
  ],
  "parent": "minecraft:recipes/root",
  "display": {
    "icon": {
      "item": "packedup:obsidianbackpack"
    },
    "title": {
      "translate": "packedup.advancement.recipes/packedup/obsidian_from_iron.title"
    },
    "description": {
      "translate": "packedup.advancement.recipes/packedup/obsidian_from_iron.description"
    },
    "frame": "task",
    "show_toast": false,
    "announce_to_chat": false,
    "hidden": false
  },
  "criteria": {
    "has_the_recipe": {
      "trigger": "minecraft:recipe_unlocked",
      "conditions": {
        "recipe": "packedup:obsidian_from_iron"
      }
    },
    "recipe_condition": {
      "trigger": "minecraft:inventory_changed",
      "conditions": {
        "items": [
          {
            "item": "packedup:ironbackpack",
            "data": 0
          }
        ]
      }
    }
  },
  "requirements": [
    [
      "has_the_recipe",
      "recipe_condition"
    ]
  ],
  "rewards": {
    "recipes": [
      "packedup:obsidian_from_iron"
    ]
  }
}