{
  "type": "packedup:backpackrecipe",
  "conditions": [
    {
      "type": "packedup_enabled",
      "backpack": "gold"
    },
    {
      "type": "forge:and",
      "values": [
        {
          "type": "packedup_enabled",
          "backpack": "copper"
        },
        {
          "type": "forge:not",
          "value": {
            "type": "forge_tag_empty",
            "tag": "ingotCopper"
          }
        }
      ]
    }
  ],
  "pattern": [
    "ILI",
    "ICI",
    "III"
  ],
  "key": {
    "I": {
      "type": "forge:ore_dict",
      "ore": "ingotGold"
    },
    "C": {
      "item": "packedup:copperbackpack"
    },
    "L": {
      "type": "forge:ore_dict",
      "ore": "ingotCopper"
    }
  },
  "result": {
    "item": "packedup:goldbackpack"
  }
}